{
    "app": {
        "name": "TanukiHQ Toriimon"
    },
    "webserver": {
        "webAddress": "localhost:5000",
        "port": 5000
    },
    "toriimon": {
        "secretKey": "testKey",
        "mailer": {
            "host": "smtp.sendgrid.net",
            "port": 587,
            "auth": {
                "user": "apikey",
                "pass": "Enter your apikey here"
            },
            "customisation": {
                "confirmation": {
                    "subject": "Confirm your email address - Tourisit"
                },
                "resetPassword": {
                    "subject": "Password reset - Tourisit"
                },
                "unknownLogin": {
                    "subject": "New login detected - Tourisit"
                }
            }
        }
    }
}